{
  "DEFAULT_ANALYSIS": "Canonical",
  "ANALYSES": {
    "Canonical": {
      "DEFAULT_CSV_FILENAME": "data/canonical/tcga_atac_nmf_k24_H_proportions.csv",
      "NPY_PROPORTIONS_FILENAME": "data/canonical/tcga_atac_nmf_k24_H_proportions.npy",
      "GRANDSCATTER_CSV_FILENAME": "data/canonical/tcga_atac_nmf_k24_H_proportions.csv",
      "GRANDSCATTER_NPY_PROPORTIONS_FILENAME": "data/canonical/tcga_atac_nmf_k24_H_proportions.npy",
      "UMAP_FILENAME": "data/canonical/tcga_atac_nmf_k24_umap_coordinates.csv",
      "ANALYSIS_METADATA_FILENAME": "data/canonical/tcga_atac_nmf_k24_metadata_sorted.csv"
    },
    "CN-aware unadjusted": {
      "DEFAULT_CSV_FILENAME": "data/cn-aware-unadjusted/confounded_nmf_k24_H_proportions.csv",
      "NPY_PROPORTIONS_FILENAME": "data/cn-aware-unadjusted/confounded_nmf_k24_H_proportions.npy",
      "GRANDSCATTER_CSV_FILENAME": "data/cn-aware-unadjusted/confounded_nmf_k24_H_proportions.csv",
      "GRANDSCATTER_NPY_PROPORTIONS_FILENAME": "data/cn-aware-unadjusted/confounded_nmf_k24_H_proportions.npy",
      "UMAP_FILENAME": "data/cn-aware-unadjusted/confounded_nmf_k24_umap_coordinates.csv",
      "ANALYSIS_METADATA_FILENAME": "data/cn-aware-unadjusted/confounded_nmf_k24_metadata_sorted.csv"
    },
    "CN-aware adjusted": {
      "DEFAULT_CSV_FILENAME": "data/cn-aware-adjusted/adjusted_nmf_k24_H_proportions.csv",
      "NPY_PROPORTIONS_FILENAME": "data/cn-aware-adjusted/adjusted_nmf_k24_H_proportions.npy",
      "GRANDSCATTER_CSV_FILENAME": "data/cn-aware-adjusted/adjusted_nmf_k24_H_proportions.csv",
      "GRANDSCATTER_NPY_PROPORTIONS_FILENAME": "data/cn-aware-adjusted/adjusted_nmf_k24_H_proportions.npy",
      "UMAP_FILENAME": "data/cn-aware-adjusted/adjusted_nmf_k24_umap_coordinates.csv",
      "ANALYSIS_METADATA_FILENAME": "data/cn-aware-adjusted/adjusted_nmf_k24_metadata_sorted.csv"
    }
  },
  "ANALYSIS_METADATA_SAMPLE_ID_COLUMN": "sample_id",
  "ANALYSIS_CANCER_TYPE_COLUMN": "cancer_type",
  "JSON_FILENAME_CANCER_TYPE_COLORS": "conf/cancer_type_color_map.json",
  "JSON_FILENAME_COMPONENT_COLORS": "conf/nmf_component_color_map.json",
  "STRIP_METADATA_FILENAME": "data/0302_corces_submitter_metadata_expanded_v2.csv",
  "STRIP_METADATA_ID_COLUMN": "submitter_id",
  "STRIP_UNKNOWN_COLOR": "#CCCCCC",
  "HEATMAP_STRIPS": [
    {
      "column": "cohort",
      "label": "Cohort",
      "palette_source": "cancer_type_colors"
    },
    {
      "column": "organ_system",
      "label": "Organ System",
      "palette": [
        "#FF0000",
        "#FF4500",
        "#32CD32",
        "#008000",
        "#006400",
        "#C2E105",
        "#FFFF00",
        "#66CDAA",
        "#8A91D0",
        "#CD5C5C",
        "#E9967A",
        "#BDB76B",
        "#808080",
        "#C0C0C0",
        "#FFFFFF"
      ]
    },
    {
      "column": "primary_site",
      "label": "Primary Site",
      "palette": [
        "#FF0000",
        "#FF4500",
        "#32CD32",
        "#008000",
        "#006400",
        "#C2E105",
        "#FFFF00",
        "#66CDAA",
        "#8A91D0",
        "#CD5C5C",
        "#E9967A",
        "#BDB76B",
        "#808080",
        "#C0C0C0",
        "#FFFFFF"
      ]
    },
    {
      "column": "histology_class",
      "label": "Histology Class",
      "palette": [
        "#0072B2",
        "#E69F00",
        "#56B4E9",
        "#009E73",
        "#F0E442",
        "#CC79A7"
      ]
    },
    {
      "column": "histology_subtype",
      "label": "Histology Subtype",
      "palette": [
        "#000000",
        "#7F7F7F",
        "#E69F00",
        "#56B4E9",
        "#009E73",
        "#F0E442",
        "#0072B2",
        "#CC79A7",
        "#117733",
        "#44AA99",
        "#DDCC77",
        "#332288",
        "#882255",
        "#A6CEE3",
        "#B2DF8A",
        "#CAB2D6"
      ]
    },
    {
      "column": "germ_layer",
      "label": "Germ Layer",
      "color_map": {
        "Ectoderm": "#56B4E9",
        "Mesoderm": "#E69F00",
        "Endoderm": "#009E73"
      }
    }
  ]
}